rinoh_typeface_carlito/Carlito-Bold.ttf
rinoh_typeface_carlito/Carlito-BoldItalic.ttf
rinoh_typeface_carlito/Carlito-Italic.ttf
rinoh_typeface_carlito/Carlito-Regular.ttf
rinoh_typeface_carlito/LICENSE
rinoh_typeface_carlito/__init__.py
rinoh_typeface_carlito-0.1.0.dist-info/METADATA
rinoh_typeface_carlito-0.1.0.dist-info/WHEEL
rinoh_typeface_carlito-0.1.0.dist-info/entry_points.txt
rinoh_typeface_carlito-0.1.0.dist-info/top_level.txt
rinoh_typeface_carlito-0.1.0.dist-info/RECORD
